{"lang.wms.fed.item04393":"货位编码","lang.wms.fed.customerCode":"货主编码","lang.wms.fed.outWaveCode":"外部波次号","lang.wms.fed.realTerms":"实际品数","lang.wms.fed.applyOwner":"适用货主","lang.wms.fed.suitOwner":"适用货主","lang.wms.fed.commodityCoding":"商品编码","lang.wms.fed.digitsLimit":"位数限制","lang.wms.fed.diy.print_opportunity.transferBin":"转移料箱","lang.wms.fed.externalWaveNumber":"外部波次号","lang.wms.fed.ownerCode":"货主编码","lang.wms.fed.contentHunt":"提示","lang.wms.fed.startPickingTheGoods":"拣货完成","lang.wms.fed.inputContainerNoNote":"请输入容器编码","lang.wms.fed.limit":"限制","lang.wms.fed.expiryDate":"到期日期","lang.wms.fed.item1068":"计划品数","lang.wms.fed.item1069":"计划件数","lang.wms.fed.gasGrpCount":"任务数量","lang.wms.fed.confirmCancel":"确认取消","lang.wms.fed.createdTheStocktake":"创建","lang.wms.fed.realNums":"实际件数","lang.wms.fed.item1070":"实际品数","lang.wms.fed.item1071":"实际件数","lang.wms.fed.pleaseEnterAPositiveInteger":"请输入正整数","lang.wms.fed.shopBarcode":"商品条码","lang.wms.fed.taskAmount":"任务数量","lang.wms.fed.originOrderNo":"源单号","lang.wms.fed.planNums":"计划件数","lang.wms.fed.FORBID":"禁用","lang.gps.fed.standardAvailability":"利用率基准","lang.wms.fed.inputContainerCode":"请输入容器编码","lang.wms.fed.create":"创建","lang.wms.fed.unitsLimit":"位数限制","lang.wms.fed.skuCode":"商品编码","lang.wms.fed.documentType":"单据类型","lang.wms.fed.pickUpTheGoods":"拣货完成","lang.wms.fed.expireDate":"到期日期","lang.wms.fed.serialNumber":"创建人","lang.wms.fed.outOfStockTime":"报缺时间","lang.wms.fed.fullBoxSuccess":"满箱成功","lang.wms.fed.gasGroup":"任务分组","lang.wms.fed.waybillCode":"运单号","lang.wms.fed.generatingStocktake":"生成盘点","lang.wms.fed.pleaseInputPosInt":"请输入正整数","lang.wms.fed.doPrintShoppingList":"打印购物清单","lang.wms.fed.disable":"禁用","lang.wms.fed.item0962":"截单时间","lang.wms.fed.add_stocktake":"生成盘点","lang.wms.fed.sports":"运动","lang.wms.fed.cancel":"取消","lang.wms.fed.createDate":"创建日期","lang.wms.fed.closedStocktake":"取消","lang.wms.fed.trayNo":"托盘号","lang.wms.fed.creationDate":"创建日期","lang.wms.fed.byShelfCode":"按货架编码","lang.wms.fed.confirmHandling":"确认处理","lang.wms.fed.typeOfOutOfStock":"报缺类型","lang.wms.fed.shoppingListPrint":"打印购物清单","lang.wms.fed.accordingToTheStorageRackNumber":"按货架编码","lang.wms.fed.whetherToConfirmTheCancellationOfTheCurrentlyTask":"确认处理","lang.gps.fed.limit":"限制","lang.wms.fed.barcode":"商品条码","lang.wms.fed.batchProperty10":"批次属性10","lang.wms.fed.pickLackWorkType":"单据类型","lang.wms.fed.waybillNo":"运单号","lang.wms.fed.sport":"运动","lang.wms.fed.stocktake":"盘点","lang.wms.fed.planTerms":"计划品数","lang.wms.fed.consigneeCompany":"收货单位","lang.wms.fed.batchPorperty10":"批次属性10","lang.wms.fed.creator":"创建人","lang.wms.fed.binCode":"货位编码","lang.wms.fed.lackReason":"报缺类型","lang.wms.fed.pickLackStatus":"处理状态","lang.wms.fed.palletCode":"托盘号","lang.wms.fed.creater":"创建人","lang.wms.fed.expectedFinishDate":"截单时间","lang.wms.fed.differentialProcessingMode":"差异处理模式","lang.wms.fed.fullSuccess":"满箱成功","lang.wms.fed.lackTime":"报缺时间","lang.wms.fed.tips":"提示","lang.wms.fed.containerNoGenerator.note":"提示","lang.wms.fed.receivingUnit":"收货单位","lang.wms.fed.transferCarton":"转移料箱","lang.wms.fed.takestock":"盘点","lang.wms.fed.differencesProcessingModel":"差异处理模式","lang.wms.fed.confirmationOfCancellation":"确认取消","lang.wms.fed.standardAvailability":"利用率基准","lang.wms.fed.gasGrpName":"任务分组","lang.wms.fed.pickLackOrderNo":"源单号","lang.wms.fed.processingState":"处理状态"}